[
    {
        "symbol": "aave",
        "price": 177.02,
        "percent_change_24h": 1.68466,
        "volume_24h": 202187201.0,
        "galaxy_score": 0.0,
        "reason": "Social activity: N/A, Price Change: 1.68466%"
    },
    {
        "symbol": "hype",
        "price": 20.97,
        "percent_change_24h": 1.32953,
        "volume_24h": 83441342.0,
        "galaxy_score": 0.0,
        "reason": "Social activity: N/A, Price Change: 1.32953%"
    },
    {
        "symbol": "leo",
        "price": 8.95,
        "percent_change_24h": 1.124,
        "volume_24h": 1835701.0,
        "galaxy_score": 0.0,
        "reason": "Social activity: N/A, Price Change: 1.124%"
    },
    {
        "symbol": "ada",
        "price": 0.698222,
        "percent_change_24h": 0.46301,
        "volume_24h": 771519720.0,
        "galaxy_score": 0.0,
        "reason": "Social activity: N/A, Price Change: 0.46301%"
    },
    {
        "symbol": "usds",
        "price": 0.999983,
        "percent_change_24h": 0.00693,
        "volume_24h": 8052439.0,
        "galaxy_score": 0.0,
        "reason": "Social activity: N/A, Price Change: 0.00693%"
    },
    {
        "symbol": "bsc-usd",
        "price": 1.0,
        "percent_change_24h": 9e-05,
        "volume_24h": 68250101.0,
        "galaxy_score": 0.0,
        "reason": "Social activity: N/A, Price Change: 9e-05%"
    },
    {
        "symbol": "PUSH-USDT",
        "price": 0.0,
        "percent_change_24h": 0.0,
        "volume_24h": 0.0,
        "galaxy_score": 0.0,
        "reason": "Social activity: N/A, Price Change: 0.0%"
    },
    {
        "symbol": "PUSH-BTC",
        "price": 0.0,
        "percent_change_24h": 0.0,
        "volume_24h": 0.0,
        "galaxy_score": 0.0,
        "reason": "Social activity: N/A, Price Change: 0.0%"
    },
    {
        "symbol": "PURR-USDT",
        "price": 0.0,
        "percent_change_24h": 0.0,
        "volume_24h": 0.0,
        "galaxy_score": 0.0,
        "reason": "Social activity: N/A, Price Change: 0.0%"
    },
    {
        "symbol": "PUNDIX-USDT",
        "price": 0.0,
        "percent_change_24h": 0.0,
        "volume_24h": 0.0,
        "galaxy_score": 0.0,
        "reason": "Social activity: N/A, Price Change: 0.0%"
    }
]