[
    {
        "symbol": "uni",
        "price": 8.48,
        "percent_change_24h": 21.93552,
        "volume_24h": 1450116005.0,
        "galaxy_score": 0.0,
        "reason": "Social activity: N/A, Price Change: 21.93552%"
    },
    {
        "symbol": "hype",
        "price": 41.93,
        "percent_change_24h": 8.52982,
        "volume_24h": 515368989.0,
        "galaxy_score": 0.0,
        "reason": "Social activity: N/A, Price Change: 8.52982%"
    },
    {
        "symbol": "aave",
        "price": 306.23,
        "percent_change_24h": 6.78843,
        "volume_24h": 1044883618.0,
        "galaxy_score": 0.0,
        "reason": "Social activity: N/A, Price Change: 6.78843%"
    },
    {
        "symbol": "link",
        "price": 15.29,
        "percent_change_24h": 5.60931,
        "volume_24h": 602520900.0,
        "galaxy_score": 0.0,
        "reason": "Social activity: N/A, Price Change: 5.60931%"
    },
    {
        "symbol": "wsteth",
        "price": 3378.4,
        "percent_change_24h": 3.37115,
        "volume_24h": 18350386.0,
        "galaxy_score": 0.0,
        "reason": "Social activity: N/A, Price Change: 3.37115%"
    },
    {
        "symbol": "bch",
        "price": 439.61,
        "percent_change_24h": 3.32626,
        "volume_24h": 367718210.0,
        "galaxy_score": 0.0,
        "reason": "Social activity: N/A, Price Change: 3.32626%"
    },
    {
        "symbol": "eth",
        "price": 2803.79,
        "percent_change_24h": 3.28906,
        "volume_24h": 37489095801.0,
        "galaxy_score": 0.0,
        "reason": "Social activity: N/A, Price Change: 3.28906%"
    },
    {
        "symbol": "near",
        "price": 2.64,
        "percent_change_24h": 3.26169,
        "volume_24h": 202505776.0,
        "galaxy_score": 0.0,
        "reason": "Social activity: N/A, Price Change: 3.26169%"
    },
    {
        "symbol": "weth",
        "price": 2799.65,
        "percent_change_24h": 3.24017,
        "volume_24h": 977851264.0,
        "galaxy_score": 0.0,
        "reason": "Social activity: N/A, Price Change: 3.24017%"
    },
    {
        "symbol": "steth",
        "price": 2799.4,
        "percent_change_24h": 3.23857,
        "volume_24h": 38691491.0,
        "galaxy_score": 0.0,
        "reason": "Social activity: N/A, Price Change: 3.23857%"
    }
]